{
  "version": "v1",
  "blocklist": [],
  "data": [
    {
      "schema_version": "1.0.0",
      "id": "bonsaiPR",
      "name": "BonsaiPR",
      "tagline": "On-demand Bonsai builds with merged PRs for IfcOpenShell.",
      "version": "0.8.5-alpha260411",
      "type": "add-on",
      "maintainer": "falken10vdl <falken10vdl@gmail.com>",
      "license": [
        "SPDX:GPL-3.0-or-later"
      ],
      "blender_version_min": "4.2.0",
      "website": "https://github.com/falken10vdl/bonsaiPR",
      "permissions": {
        "network": "For update checks and remote asset downloads",
        "files": "Load and save IFCs, BCF, and other project files from disk",
        "clipboard": "Copy and paste error logs"
      },
      "tags": [
        "3D View",
        "Add Mesh",
        "Animation",
        "Camera",
        "Development",
        "Import-Export",
        "Lighting",
        "Material",
        "Modeling",
        "Mesh",
        "Node",
        "Object",
        "Pipeline",
        "Render",
        "Scene",
        "System",
        "User Interface",
        "UV"
      ],
      "platforms": [
        "linux-x64"
      ],
      "python_versions": [
        "3.11"
      ],
      "archive_url": "https://github.com/falken10vdl/bonsaiPR/releases/download/v0.8.5-alpha2604111335/bonsaiPR_py311-0.8.5-alpha2604111335-linux-x64.zip",
      "archive_size": 153762946,
      "archive_hash": "sha256:2827e39cb52166eacea4e986cb77230b7ae7dde2d88ad6f0f96e8baab8beabd5"
    },
    {
      "schema_version": "1.0.0",
      "id": "bonsaiPR",
      "name": "BonsaiPR",
      "tagline": "On-demand Bonsai builds with merged PRs for IfcOpenShell.",
      "version": "0.8.5-alpha260411",
      "type": "add-on",
      "maintainer": "falken10vdl <falken10vdl@gmail.com>",
      "license": [
        "SPDX:GPL-3.0-or-later"
      ],
      "blender_version_min": "4.2.0",
      "website": "https://github.com/falken10vdl/bonsaiPR",
      "permissions": {
        "network": "For update checks and remote asset downloads",
        "files": "Load and save IFCs, BCF, and other project files from disk",
        "clipboard": "Copy and paste error logs"
      },
      "tags": [
        "3D View",
        "Add Mesh",
        "Animation",
        "Camera",
        "Development",
        "Import-Export",
        "Lighting",
        "Material",
        "Modeling",
        "Mesh",
        "Node",
        "Object",
        "Pipeline",
        "Render",
        "Scene",
        "System",
        "User Interface",
        "UV"
      ],
      "platforms": [
        "macos-x64"
      ],
      "python_versions": [
        "3.11"
      ],
      "archive_url": "https://github.com/falken10vdl/bonsaiPR/releases/download/v0.8.5-alpha2604111335/bonsaiPR_py311-0.8.5-alpha2604111335-macos-x64.zip",
      "archive_size": 140452312,
      "archive_hash": "sha256:c4d2159fc92bcfe3bbc4db3fae9added3831683b2d4021faf5f86dd54cb5ee49"
    },
    {
      "schema_version": "1.0.0",
      "id": "bonsaiPR",
      "name": "BonsaiPR",
      "tagline": "On-demand Bonsai builds with merged PRs for IfcOpenShell.",
      "version": "0.8.5-alpha260411",
      "type": "add-on",
      "maintainer": "falken10vdl <falken10vdl@gmail.com>",
      "license": [
        "SPDX:GPL-3.0-or-later"
      ],
      "blender_version_min": "4.2.0",
      "website": "https://github.com/falken10vdl/bonsaiPR",
      "permissions": {
        "network": "For update checks and remote asset downloads",
        "files": "Load and save IFCs, BCF, and other project files from disk",
        "clipboard": "Copy and paste error logs"
      },
      "tags": [
        "3D View",
        "Add Mesh",
        "Animation",
        "Camera",
        "Development",
        "Import-Export",
        "Lighting",
        "Material",
        "Modeling",
        "Mesh",
        "Node",
        "Object",
        "Pipeline",
        "Render",
        "Scene",
        "System",
        "User Interface",
        "UV"
      ],
      "platforms": [
        "macos-arm64"
      ],
      "python_versions": [
        "3.11"
      ],
      "archive_url": "https://github.com/falken10vdl/bonsaiPR/releases/download/v0.8.5-alpha2604111335/bonsaiPR_py311-0.8.5-alpha2604111335-macos-arm64.zip",
      "archive_size": 137414481,
      "archive_hash": "sha256:31b632de873119fb239fa6a66f7671e1c144dc4e880cffac45e9e491336a9ca8"
    },
    {
      "schema_version": "1.0.0",
      "id": "bonsaiPR",
      "name": "BonsaiPR",
      "tagline": "On-demand Bonsai builds with merged PRs for IfcOpenShell.",
      "version": "0.8.5-alpha260411",
      "type": "add-on",
      "maintainer": "falken10vdl <falken10vdl@gmail.com>",
      "license": [
        "SPDX:GPL-3.0-or-later"
      ],
      "blender_version_min": "4.2.0",
      "website": "https://github.com/falken10vdl/bonsaiPR",
      "permissions": {
        "network": "For update checks and remote asset downloads",
        "files": "Load and save IFCs, BCF, and other project files from disk",
        "clipboard": "Copy and paste error logs"
      },
      "tags": [
        "3D View",
        "Add Mesh",
        "Animation",
        "Camera",
        "Development",
        "Import-Export",
        "Lighting",
        "Material",
        "Modeling",
        "Mesh",
        "Node",
        "Object",
        "Pipeline",
        "Render",
        "Scene",
        "System",
        "User Interface",
        "UV"
      ],
      "platforms": [
        "windows-x64"
      ],
      "python_versions": [
        "3.11"
      ],
      "archive_url": "https://github.com/falken10vdl/bonsaiPR/releases/download/v0.8.5-alpha2604111335/bonsaiPR_py311-0.8.5-alpha2604111335-windows-x64.zip",
      "archive_size": 124491787,
      "archive_hash": "sha256:c15483150b2d6aa5dc7d20f40736c9c8c8d7b03541acc5bf3e6207fd4def2fe2"
    },
    {
      "schema_version": "1.0.0",
      "id": "bonsaiPR",
      "name": "BonsaiPR",
      "tagline": "On-demand Bonsai builds with merged PRs for IfcOpenShell.",
      "version": "0.8.5-alpha260411",
      "type": "add-on",
      "maintainer": "falken10vdl <falken10vdl@gmail.com>",
      "license": [
        "SPDX:GPL-3.0-or-later"
      ],
      "blender_version_min": "5.1.0",
      "website": "https://github.com/falken10vdl/bonsaiPR",
      "permissions": {
        "network": "For update checks and remote asset downloads",
        "files": "Load and save IFCs, BCF, and other project files from disk",
        "clipboard": "Copy and paste error logs"
      },
      "tags": [
        "3D View",
        "Add Mesh",
        "Animation",
        "Camera",
        "Development",
        "Import-Export",
        "Lighting",
        "Material",
        "Modeling",
        "Mesh",
        "Node",
        "Object",
        "Pipeline",
        "Render",
        "Scene",
        "System",
        "User Interface",
        "UV"
      ],
      "platforms": [
        "linux-x64"
      ],
      "python_versions": [
        "3.13"
      ],
      "archive_url": "https://github.com/falken10vdl/bonsaiPR/releases/download/v0.8.5-alpha2604111335/bonsaiPR_py313-0.8.5-alpha2604111335-linux-x64.zip",
      "archive_size": 153239059,
      "archive_hash": "sha256:d7646b2559074a93b0c5663ea094accdac92aee0b3db1b12866a9d134c07affc"
    },
    {
      "schema_version": "1.0.0",
      "id": "bonsaiPR",
      "name": "BonsaiPR",
      "tagline": "On-demand Bonsai builds with merged PRs for IfcOpenShell.",
      "version": "0.8.5-alpha260411",
      "type": "add-on",
      "maintainer": "falken10vdl <falken10vdl@gmail.com>",
      "license": [
        "SPDX:GPL-3.0-or-later"
      ],
      "blender_version_min": "5.1.0",
      "website": "https://github.com/falken10vdl/bonsaiPR",
      "permissions": {
        "network": "For update checks and remote asset downloads",
        "files": "Load and save IFCs, BCF, and other project files from disk",
        "clipboard": "Copy and paste error logs"
      },
      "tags": [
        "3D View",
        "Add Mesh",
        "Animation",
        "Camera",
        "Development",
        "Import-Export",
        "Lighting",
        "Material",
        "Modeling",
        "Mesh",
        "Node",
        "Object",
        "Pipeline",
        "Render",
        "Scene",
        "System",
        "User Interface",
        "UV"
      ],
      "platforms": [
        "macos-arm64"
      ],
      "python_versions": [
        "3.13"
      ],
      "archive_url": "https://github.com/falken10vdl/bonsaiPR/releases/download/v0.8.5-alpha2604111335/bonsaiPR_py313-0.8.5-alpha2604111335-macos-arm64.zip",
      "archive_size": 137354401,
      "archive_hash": "sha256:e962be63e02f24bd34b839226d6d0cabf37b5e0a653381b729bb4b30dc9b7b4b"
    },
    {
      "schema_version": "1.0.0",
      "id": "bonsaiPR",
      "name": "BonsaiPR",
      "tagline": "On-demand Bonsai builds with merged PRs for IfcOpenShell.",
      "version": "0.8.5-alpha260411",
      "type": "add-on",
      "maintainer": "falken10vdl <falken10vdl@gmail.com>",
      "license": [
        "SPDX:GPL-3.0-or-later"
      ],
      "blender_version_min": "5.1.0",
      "website": "https://github.com/falken10vdl/bonsaiPR",
      "permissions": {
        "network": "For update checks and remote asset downloads",
        "files": "Load and save IFCs, BCF, and other project files from disk",
        "clipboard": "Copy and paste error logs"
      },
      "tags": [
        "3D View",
        "Add Mesh",
        "Animation",
        "Camera",
        "Development",
        "Import-Export",
        "Lighting",
        "Material",
        "Modeling",
        "Mesh",
        "Node",
        "Object",
        "Pipeline",
        "Render",
        "Scene",
        "System",
        "User Interface",
        "UV"
      ],
      "platforms": [
        "windows-x64"
      ],
      "python_versions": [
        "3.13"
      ],
      "archive_url": "https://github.com/falken10vdl/bonsaiPR/releases/download/v0.8.5-alpha2604111335/bonsaiPR_py313-0.8.5-alpha2604111335-windows-x64.zip",
      "archive_size": 124245271,
      "archive_hash": "sha256:6326294944f3aa29dcb09d0ca9358af7961b9ad0b63df7d94eeafb4417054c0e"
    }
  ]
}