{
  "version": "v1",
  "blocklist": [],
  "data": [
    {
      "schema_version": "1.0.0",
      "id": "bonsaiPR",
      "name": "BonsaiPR",
      "tagline": "On-demand Bonsai builds with merged PRs for IfcOpenShell.",
      "version": "0.8.5-alpha260412",
      "type": "add-on",
      "maintainer": "falken10vdl <falken10vdl@gmail.com>",
      "license": [
        "SPDX:GPL-3.0-or-later"
      ],
      "blender_version_min": "4.2.0",
      "website": "https://github.com/falken10vdl/bonsaiPR",
      "permissions": {
        "network": "For update checks and remote asset downloads",
        "files": "Load and save IFCs, BCF, and other project files from disk",
        "clipboard": "Copy and paste error logs"
      },
      "tags": [
        "3D View",
        "Add Mesh",
        "Animation",
        "Camera",
        "Development",
        "Import-Export",
        "Lighting",
        "Material",
        "Modeling",
        "Mesh",
        "Node",
        "Object",
        "Pipeline",
        "Render",
        "Scene",
        "System",
        "User Interface",
        "UV"
      ],
      "platforms": [
        "linux-x64"
      ],
      "python_versions": [
        "3.11"
      ],
      "archive_url": "https://github.com/falken10vdl/bonsaiPR/releases/download/v0.8.5-alpha2604122135/bonsaiPR_py311-0.8.5-alpha2604122135-linux-x64.zip",
      "archive_size": 153799153,
      "archive_hash": "sha256:f4810a8561d6e30ec1dd7ec2099b1a709af1b293c64eb4caf97d28f2ecf78b32"
    },
    {
      "schema_version": "1.0.0",
      "id": "bonsaiPR",
      "name": "BonsaiPR",
      "tagline": "On-demand Bonsai builds with merged PRs for IfcOpenShell.",
      "version": "0.8.5-alpha260412",
      "type": "add-on",
      "maintainer": "falken10vdl <falken10vdl@gmail.com>",
      "license": [
        "SPDX:GPL-3.0-or-later"
      ],
      "blender_version_min": "4.2.0",
      "website": "https://github.com/falken10vdl/bonsaiPR",
      "permissions": {
        "network": "For update checks and remote asset downloads",
        "files": "Load and save IFCs, BCF, and other project files from disk",
        "clipboard": "Copy and paste error logs"
      },
      "tags": [
        "3D View",
        "Add Mesh",
        "Animation",
        "Camera",
        "Development",
        "Import-Export",
        "Lighting",
        "Material",
        "Modeling",
        "Mesh",
        "Node",
        "Object",
        "Pipeline",
        "Render",
        "Scene",
        "System",
        "User Interface",
        "UV"
      ],
      "platforms": [
        "macos-x64"
      ],
      "python_versions": [
        "3.11"
      ],
      "archive_url": "https://github.com/falken10vdl/bonsaiPR/releases/download/v0.8.5-alpha2604122135/bonsaiPR_py311-0.8.5-alpha2604122135-macos-x64.zip",
      "archive_size": 140459802,
      "archive_hash": "sha256:37e1bb0eaf9cdcf0ebfcc045a528471af26bef41ae6a29c904fc541f727cada3"
    },
    {
      "schema_version": "1.0.0",
      "id": "bonsaiPR",
      "name": "BonsaiPR",
      "tagline": "On-demand Bonsai builds with merged PRs for IfcOpenShell.",
      "version": "0.8.5-alpha260412",
      "type": "add-on",
      "maintainer": "falken10vdl <falken10vdl@gmail.com>",
      "license": [
        "SPDX:GPL-3.0-or-later"
      ],
      "blender_version_min": "4.2.0",
      "website": "https://github.com/falken10vdl/bonsaiPR",
      "permissions": {
        "network": "For update checks and remote asset downloads",
        "files": "Load and save IFCs, BCF, and other project files from disk",
        "clipboard": "Copy and paste error logs"
      },
      "tags": [
        "3D View",
        "Add Mesh",
        "Animation",
        "Camera",
        "Development",
        "Import-Export",
        "Lighting",
        "Material",
        "Modeling",
        "Mesh",
        "Node",
        "Object",
        "Pipeline",
        "Render",
        "Scene",
        "System",
        "User Interface",
        "UV"
      ],
      "platforms": [
        "macos-arm64"
      ],
      "python_versions": [
        "3.11"
      ],
      "archive_url": "https://github.com/falken10vdl/bonsaiPR/releases/download/v0.8.5-alpha2604122135/bonsaiPR_py311-0.8.5-alpha2604122135-macos-arm64.zip",
      "archive_size": 137453046,
      "archive_hash": "sha256:3b8d6a84cd46c28a68ce17d94fd7e498143201739feb3d495bb32576b32589d0"
    },
    {
      "schema_version": "1.0.0",
      "id": "bonsaiPR",
      "name": "BonsaiPR",
      "tagline": "On-demand Bonsai builds with merged PRs for IfcOpenShell.",
      "version": "0.8.5-alpha260412",
      "type": "add-on",
      "maintainer": "falken10vdl <falken10vdl@gmail.com>",
      "license": [
        "SPDX:GPL-3.0-or-later"
      ],
      "blender_version_min": "4.2.0",
      "website": "https://github.com/falken10vdl/bonsaiPR",
      "permissions": {
        "network": "For update checks and remote asset downloads",
        "files": "Load and save IFCs, BCF, and other project files from disk",
        "clipboard": "Copy and paste error logs"
      },
      "tags": [
        "3D View",
        "Add Mesh",
        "Animation",
        "Camera",
        "Development",
        "Import-Export",
        "Lighting",
        "Material",
        "Modeling",
        "Mesh",
        "Node",
        "Object",
        "Pipeline",
        "Render",
        "Scene",
        "System",
        "User Interface",
        "UV"
      ],
      "platforms": [
        "windows-x64"
      ],
      "python_versions": [
        "3.11"
      ],
      "archive_url": "https://github.com/falken10vdl/bonsaiPR/releases/download/v0.8.5-alpha2604122135/bonsaiPR_py311-0.8.5-alpha2604122135-windows-x64.zip",
      "archive_size": 124528249,
      "archive_hash": "sha256:7e876a667a01aab81ade1680e8b14cd825f527aadfb6c6624f568b46fd295103"
    },
    {
      "schema_version": "1.0.0",
      "id": "bonsaiPR",
      "name": "BonsaiPR",
      "tagline": "On-demand Bonsai builds with merged PRs for IfcOpenShell.",
      "version": "0.8.5-alpha260412",
      "type": "add-on",
      "maintainer": "falken10vdl <falken10vdl@gmail.com>",
      "license": [
        "SPDX:GPL-3.0-or-later"
      ],
      "blender_version_min": "5.1.0",
      "website": "https://github.com/falken10vdl/bonsaiPR",
      "permissions": {
        "network": "For update checks and remote asset downloads",
        "files": "Load and save IFCs, BCF, and other project files from disk",
        "clipboard": "Copy and paste error logs"
      },
      "tags": [
        "3D View",
        "Add Mesh",
        "Animation",
        "Camera",
        "Development",
        "Import-Export",
        "Lighting",
        "Material",
        "Modeling",
        "Mesh",
        "Node",
        "Object",
        "Pipeline",
        "Render",
        "Scene",
        "System",
        "User Interface",
        "UV"
      ],
      "platforms": [
        "linux-x64"
      ],
      "python_versions": [
        "3.13"
      ],
      "archive_url": "https://github.com/falken10vdl/bonsaiPR/releases/download/v0.8.5-alpha2604122135/bonsaiPR_py313-0.8.5-alpha2604122135-linux-x64.zip",
      "archive_size": 153275728,
      "archive_hash": "sha256:3bff45e0c645d1cd792c35932fa6a36aaa8956819374d8e0e07bb7f595f04846"
    },
    {
      "schema_version": "1.0.0",
      "id": "bonsaiPR",
      "name": "BonsaiPR",
      "tagline": "On-demand Bonsai builds with merged PRs for IfcOpenShell.",
      "version": "0.8.5-alpha260412",
      "type": "add-on",
      "maintainer": "falken10vdl <falken10vdl@gmail.com>",
      "license": [
        "SPDX:GPL-3.0-or-later"
      ],
      "blender_version_min": "5.1.0",
      "website": "https://github.com/falken10vdl/bonsaiPR",
      "permissions": {
        "network": "For update checks and remote asset downloads",
        "files": "Load and save IFCs, BCF, and other project files from disk",
        "clipboard": "Copy and paste error logs"
      },
      "tags": [
        "3D View",
        "Add Mesh",
        "Animation",
        "Camera",
        "Development",
        "Import-Export",
        "Lighting",
        "Material",
        "Modeling",
        "Mesh",
        "Node",
        "Object",
        "Pipeline",
        "Render",
        "Scene",
        "System",
        "User Interface",
        "UV"
      ],
      "platforms": [
        "macos-arm64"
      ],
      "python_versions": [
        "3.13"
      ],
      "archive_url": "https://github.com/falken10vdl/bonsaiPR/releases/download/v0.8.5-alpha2604122135/bonsaiPR_py313-0.8.5-alpha2604122135-macos-arm64.zip",
      "archive_size": 137391070,
      "archive_hash": "sha256:1c6ff5c7b59a6a2336a49cd127093d302c75da2cd49122802f95fbb1b5af4a11"
    },
    {
      "schema_version": "1.0.0",
      "id": "bonsaiPR",
      "name": "BonsaiPR",
      "tagline": "On-demand Bonsai builds with merged PRs for IfcOpenShell.",
      "version": "0.8.5-alpha260412",
      "type": "add-on",
      "maintainer": "falken10vdl <falken10vdl@gmail.com>",
      "license": [
        "SPDX:GPL-3.0-or-later"
      ],
      "blender_version_min": "5.1.0",
      "website": "https://github.com/falken10vdl/bonsaiPR",
      "permissions": {
        "network": "For update checks and remote asset downloads",
        "files": "Load and save IFCs, BCF, and other project files from disk",
        "clipboard": "Copy and paste error logs"
      },
      "tags": [
        "3D View",
        "Add Mesh",
        "Animation",
        "Camera",
        "Development",
        "Import-Export",
        "Lighting",
        "Material",
        "Modeling",
        "Mesh",
        "Node",
        "Object",
        "Pipeline",
        "Render",
        "Scene",
        "System",
        "User Interface",
        "UV"
      ],
      "platforms": [
        "windows-x64"
      ],
      "python_versions": [
        "3.13"
      ],
      "archive_url": "https://github.com/falken10vdl/bonsaiPR/releases/download/v0.8.5-alpha2604122135/bonsaiPR_py313-0.8.5-alpha2604122135-windows-x64.zip",
      "archive_size": 124281353,
      "archive_hash": "sha256:a090a3bf872848871c1142400eac4108c0bec429dd355aabb422ea7b8ebb2b8c"
    }
  ]
}