{
  "version": "v1",
  "blocklist": [],
  "data": [
    {
      "schema_version": "1.0.0",
      "id": "bonsaiPR",
      "name": "BonsaiPR",
      "tagline": "On-demand Bonsai builds with merged PRs for IfcOpenShell.",
      "version": "0.8.5-alpha260410",
      "type": "add-on",
      "maintainer": "falken10vdl <falken10vdl@gmail.com>",
      "license": [
        "SPDX:GPL-3.0-or-later"
      ],
      "blender_version_min": "4.2.0",
      "website": "https://github.com/falken10vdl/bonsaiPR",
      "permissions": {
        "network": "For update checks and remote asset downloads",
        "files": "Load and save IFCs, BCF, and other project files from disk",
        "clipboard": "Copy and paste error logs"
      },
      "tags": [
        "3D View",
        "Add Mesh",
        "Animation",
        "Camera",
        "Development",
        "Import-Export",
        "Lighting",
        "Material",
        "Modeling",
        "Mesh",
        "Node",
        "Object",
        "Pipeline",
        "Render",
        "Scene",
        "System",
        "User Interface",
        "UV"
      ],
      "platforms": [
        "linux-x64"
      ],
      "python_versions": [
        "3.11"
      ],
      "archive_url": "https://github.com/falken10vdl/bonsaiPR/releases/download/v0.8.5-alpha2604100135/bonsaiPR_py311-0.8.5-alpha2604100135-linux-x64.zip",
      "archive_size": 153783223,
      "archive_hash": "sha256:decf8ea7e7f70198311b8fa3c42b021a74d9588ee62ddba29b2e59b0c9debb00"
    },
    {
      "schema_version": "1.0.0",
      "id": "bonsaiPR",
      "name": "BonsaiPR",
      "tagline": "On-demand Bonsai builds with merged PRs for IfcOpenShell.",
      "version": "0.8.5-alpha260410",
      "type": "add-on",
      "maintainer": "falken10vdl <falken10vdl@gmail.com>",
      "license": [
        "SPDX:GPL-3.0-or-later"
      ],
      "blender_version_min": "4.2.0",
      "website": "https://github.com/falken10vdl/bonsaiPR",
      "permissions": {
        "network": "For update checks and remote asset downloads",
        "files": "Load and save IFCs, BCF, and other project files from disk",
        "clipboard": "Copy and paste error logs"
      },
      "tags": [
        "3D View",
        "Add Mesh",
        "Animation",
        "Camera",
        "Development",
        "Import-Export",
        "Lighting",
        "Material",
        "Modeling",
        "Mesh",
        "Node",
        "Object",
        "Pipeline",
        "Render",
        "Scene",
        "System",
        "User Interface",
        "UV"
      ],
      "platforms": [
        "macos-x64"
      ],
      "python_versions": [
        "3.11"
      ],
      "archive_url": "https://github.com/falken10vdl/bonsaiPR/releases/download/v0.8.5-alpha2604100135/bonsaiPR_py311-0.8.5-alpha2604100135-macos-x64.zip",
      "archive_size": 140472640,
      "archive_hash": "sha256:8b6c766fc2ca4d5608c19273a932486684451d9310d4a85e703158dd48e30515"
    },
    {
      "schema_version": "1.0.0",
      "id": "bonsaiPR",
      "name": "BonsaiPR",
      "tagline": "On-demand Bonsai builds with merged PRs for IfcOpenShell.",
      "version": "0.8.5-alpha260410",
      "type": "add-on",
      "maintainer": "falken10vdl <falken10vdl@gmail.com>",
      "license": [
        "SPDX:GPL-3.0-or-later"
      ],
      "blender_version_min": "4.2.0",
      "website": "https://github.com/falken10vdl/bonsaiPR",
      "permissions": {
        "network": "For update checks and remote asset downloads",
        "files": "Load and save IFCs, BCF, and other project files from disk",
        "clipboard": "Copy and paste error logs"
      },
      "tags": [
        "3D View",
        "Add Mesh",
        "Animation",
        "Camera",
        "Development",
        "Import-Export",
        "Lighting",
        "Material",
        "Modeling",
        "Mesh",
        "Node",
        "Object",
        "Pipeline",
        "Render",
        "Scene",
        "System",
        "User Interface",
        "UV"
      ],
      "platforms": [
        "macos-arm64"
      ],
      "python_versions": [
        "3.11"
      ],
      "archive_url": "https://github.com/falken10vdl/bonsaiPR/releases/download/v0.8.5-alpha2604100135/bonsaiPR_py311-0.8.5-alpha2604100135-macos-arm64.zip",
      "archive_size": 137434760,
      "archive_hash": "sha256:aaa5a79522a37c4f483aa890f33a34ca17e110b946da85fbe22fb7cc2b0ccf88"
    },
    {
      "schema_version": "1.0.0",
      "id": "bonsaiPR",
      "name": "BonsaiPR",
      "tagline": "On-demand Bonsai builds with merged PRs for IfcOpenShell.",
      "version": "0.8.5-alpha260410",
      "type": "add-on",
      "maintainer": "falken10vdl <falken10vdl@gmail.com>",
      "license": [
        "SPDX:GPL-3.0-or-later"
      ],
      "blender_version_min": "4.2.0",
      "website": "https://github.com/falken10vdl/bonsaiPR",
      "permissions": {
        "network": "For update checks and remote asset downloads",
        "files": "Load and save IFCs, BCF, and other project files from disk",
        "clipboard": "Copy and paste error logs"
      },
      "tags": [
        "3D View",
        "Add Mesh",
        "Animation",
        "Camera",
        "Development",
        "Import-Export",
        "Lighting",
        "Material",
        "Modeling",
        "Mesh",
        "Node",
        "Object",
        "Pipeline",
        "Render",
        "Scene",
        "System",
        "User Interface",
        "UV"
      ],
      "platforms": [
        "windows-x64"
      ],
      "python_versions": [
        "3.11"
      ],
      "archive_url": "https://github.com/falken10vdl/bonsaiPR/releases/download/v0.8.5-alpha2604100135/bonsaiPR_py311-0.8.5-alpha2604100135-windows-x64.zip",
      "archive_size": 124512380,
      "archive_hash": "sha256:8378972ba6b7ab5c060364119e615f235c3b71f8efddf442c812ba4bc2e91561"
    },
    {
      "schema_version": "1.0.0",
      "id": "bonsaiPR",
      "name": "BonsaiPR",
      "tagline": "On-demand Bonsai builds with merged PRs for IfcOpenShell.",
      "version": "0.8.5-alpha260410",
      "type": "add-on",
      "maintainer": "falken10vdl <falken10vdl@gmail.com>",
      "license": [
        "SPDX:GPL-3.0-or-later"
      ],
      "blender_version_min": "5.1.0",
      "website": "https://github.com/falken10vdl/bonsaiPR",
      "permissions": {
        "network": "For update checks and remote asset downloads",
        "files": "Load and save IFCs, BCF, and other project files from disk",
        "clipboard": "Copy and paste error logs"
      },
      "tags": [
        "3D View",
        "Add Mesh",
        "Animation",
        "Camera",
        "Development",
        "Import-Export",
        "Lighting",
        "Material",
        "Modeling",
        "Mesh",
        "Node",
        "Object",
        "Pipeline",
        "Render",
        "Scene",
        "System",
        "User Interface",
        "UV"
      ],
      "platforms": [
        "linux-x64"
      ],
      "python_versions": [
        "3.13"
      ],
      "archive_url": "https://github.com/falken10vdl/bonsaiPR/releases/download/v0.8.5-alpha2604100135/bonsaiPR_py313-0.8.5-alpha2604100135-linux-x64.zip",
      "archive_size": 153259374,
      "archive_hash": "sha256:3139c220e1995061aee38b7278f54472bf78020396f97ae0c5985ba0cb57dede"
    },
    {
      "schema_version": "1.0.0",
      "id": "bonsaiPR",
      "name": "BonsaiPR",
      "tagline": "On-demand Bonsai builds with merged PRs for IfcOpenShell.",
      "version": "0.8.5-alpha260410",
      "type": "add-on",
      "maintainer": "falken10vdl <falken10vdl@gmail.com>",
      "license": [
        "SPDX:GPL-3.0-or-later"
      ],
      "blender_version_min": "5.1.0",
      "website": "https://github.com/falken10vdl/bonsaiPR",
      "permissions": {
        "network": "For update checks and remote asset downloads",
        "files": "Load and save IFCs, BCF, and other project files from disk",
        "clipboard": "Copy and paste error logs"
      },
      "tags": [
        "3D View",
        "Add Mesh",
        "Animation",
        "Camera",
        "Development",
        "Import-Export",
        "Lighting",
        "Material",
        "Modeling",
        "Mesh",
        "Node",
        "Object",
        "Pipeline",
        "Render",
        "Scene",
        "System",
        "User Interface",
        "UV"
      ],
      "platforms": [
        "macos-arm64"
      ],
      "python_versions": [
        "3.13"
      ],
      "archive_url": "https://github.com/falken10vdl/bonsaiPR/releases/download/v0.8.5-alpha2604100135/bonsaiPR_py313-0.8.5-alpha2604100135-macos-arm64.zip",
      "archive_size": 137374720,
      "archive_hash": "sha256:f1b073f7266979f82ed6fb0d909ea93719fc477a67214a01a8a5669cbbb43893"
    },
    {
      "schema_version": "1.0.0",
      "id": "bonsaiPR",
      "name": "BonsaiPR",
      "tagline": "On-demand Bonsai builds with merged PRs for IfcOpenShell.",
      "version": "0.8.5-alpha260410",
      "type": "add-on",
      "maintainer": "falken10vdl <falken10vdl@gmail.com>",
      "license": [
        "SPDX:GPL-3.0-or-later"
      ],
      "blender_version_min": "5.1.0",
      "website": "https://github.com/falken10vdl/bonsaiPR",
      "permissions": {
        "network": "For update checks and remote asset downloads",
        "files": "Load and save IFCs, BCF, and other project files from disk",
        "clipboard": "Copy and paste error logs"
      },
      "tags": [
        "3D View",
        "Add Mesh",
        "Animation",
        "Camera",
        "Development",
        "Import-Export",
        "Lighting",
        "Material",
        "Modeling",
        "Mesh",
        "Node",
        "Object",
        "Pipeline",
        "Render",
        "Scene",
        "System",
        "User Interface",
        "UV"
      ],
      "platforms": [
        "windows-x64"
      ],
      "python_versions": [
        "3.13"
      ],
      "archive_url": "https://github.com/falken10vdl/bonsaiPR/releases/download/v0.8.5-alpha2604100135/bonsaiPR_py313-0.8.5-alpha2604100135-windows-x64.zip",
      "archive_size": 124265869,
      "archive_hash": "sha256:7829407409f043603f8ee45b1d1c1b783acff4f470d37de2e909582c9fe40e54"
    }
  ]
}