{
  "version": "v1",
  "blocklist": [],
  "data": [
    {
      "schema_version": "1.0.0",
      "id": "bonsaiPR",
      "name": "BonsaiPR",
      "tagline": "On-demand Bonsai builds with merged PRs for IfcOpenShell.",
      "version": "0.8.5-alpha260405",
      "type": "add-on",
      "maintainer": "falken10vdl <falken10vdl@gmail.com>",
      "license": [
        "SPDX:GPL-3.0-or-later"
      ],
      "blender_version_min": "4.2.0",
      "website": "https://github.com/falken10vdl/bonsaiPR",
      "permissions": {
        "network": "For update checks and remote asset downloads",
        "files": "Load and save IFCs, BCF, and other project files from disk",
        "clipboard": "Copy and paste error logs"
      },
      "tags": [
        "3D View",
        "Add Mesh",
        "Animation",
        "Camera",
        "Development",
        "Import-Export",
        "Lighting",
        "Material",
        "Modeling",
        "Mesh",
        "Node",
        "Object",
        "Pipeline",
        "Render",
        "Scene",
        "System",
        "User Interface",
        "UV"
      ],
      "platforms": [
        "linux-x64"
      ],
      "python_versions": [
        "3.11"
      ],
      "archive_url": "https://github.com/falken10vdl/bonsaiPR/releases/download/v0.8.5-alpha2604051935/bonsaiPR_py311-0.8.5-alpha2604051935-linux-x64.zip",
      "archive_size": 153771188,
      "archive_hash": "sha256:237c7c7ddc5a4ec40053be2405ff361aa59b4429a4ac07d38b2d0c6324d1d12d"
    },
    {
      "schema_version": "1.0.0",
      "id": "bonsaiPR",
      "name": "BonsaiPR",
      "tagline": "On-demand Bonsai builds with merged PRs for IfcOpenShell.",
      "version": "0.8.5-alpha260405",
      "type": "add-on",
      "maintainer": "falken10vdl <falken10vdl@gmail.com>",
      "license": [
        "SPDX:GPL-3.0-or-later"
      ],
      "blender_version_min": "4.2.0",
      "website": "https://github.com/falken10vdl/bonsaiPR",
      "permissions": {
        "network": "For update checks and remote asset downloads",
        "files": "Load and save IFCs, BCF, and other project files from disk",
        "clipboard": "Copy and paste error logs"
      },
      "tags": [
        "3D View",
        "Add Mesh",
        "Animation",
        "Camera",
        "Development",
        "Import-Export",
        "Lighting",
        "Material",
        "Modeling",
        "Mesh",
        "Node",
        "Object",
        "Pipeline",
        "Render",
        "Scene",
        "System",
        "User Interface",
        "UV"
      ],
      "platforms": [
        "macos-x64"
      ],
      "python_versions": [
        "3.11"
      ],
      "archive_url": "https://github.com/falken10vdl/bonsaiPR/releases/download/v0.8.5-alpha2604051935/bonsaiPR_py311-0.8.5-alpha2604051935-macos-x64.zip",
      "archive_size": 140499812,
      "archive_hash": "sha256:72989374ab7d4380dd7394443b54771bebbe06353523ff0bb5778538656fd50e"
    },
    {
      "schema_version": "1.0.0",
      "id": "bonsaiPR",
      "name": "BonsaiPR",
      "tagline": "On-demand Bonsai builds with merged PRs for IfcOpenShell.",
      "version": "0.8.5-alpha260405",
      "type": "add-on",
      "maintainer": "falken10vdl <falken10vdl@gmail.com>",
      "license": [
        "SPDX:GPL-3.0-or-later"
      ],
      "blender_version_min": "4.2.0",
      "website": "https://github.com/falken10vdl/bonsaiPR",
      "permissions": {
        "network": "For update checks and remote asset downloads",
        "files": "Load and save IFCs, BCF, and other project files from disk",
        "clipboard": "Copy and paste error logs"
      },
      "tags": [
        "3D View",
        "Add Mesh",
        "Animation",
        "Camera",
        "Development",
        "Import-Export",
        "Lighting",
        "Material",
        "Modeling",
        "Mesh",
        "Node",
        "Object",
        "Pipeline",
        "Render",
        "Scene",
        "System",
        "User Interface",
        "UV"
      ],
      "platforms": [
        "macos-arm64"
      ],
      "python_versions": [
        "3.11"
      ],
      "archive_url": "https://github.com/falken10vdl/bonsaiPR/releases/download/v0.8.5-alpha2604051935/bonsaiPR_py311-0.8.5-alpha2604051935-macos-arm64.zip",
      "archive_size": 137508529,
      "archive_hash": "sha256:8524cea7ebda8d7a7cf26356dd0c672bcf1f1dc574063dd0b0cd6e64c4bf2c96"
    },
    {
      "schema_version": "1.0.0",
      "id": "bonsaiPR",
      "name": "BonsaiPR",
      "tagline": "On-demand Bonsai builds with merged PRs for IfcOpenShell.",
      "version": "0.8.5-alpha260405",
      "type": "add-on",
      "maintainer": "falken10vdl <falken10vdl@gmail.com>",
      "license": [
        "SPDX:GPL-3.0-or-later"
      ],
      "blender_version_min": "4.2.0",
      "website": "https://github.com/falken10vdl/bonsaiPR",
      "permissions": {
        "network": "For update checks and remote asset downloads",
        "files": "Load and save IFCs, BCF, and other project files from disk",
        "clipboard": "Copy and paste error logs"
      },
      "tags": [
        "3D View",
        "Add Mesh",
        "Animation",
        "Camera",
        "Development",
        "Import-Export",
        "Lighting",
        "Material",
        "Modeling",
        "Mesh",
        "Node",
        "Object",
        "Pipeline",
        "Render",
        "Scene",
        "System",
        "User Interface",
        "UV"
      ],
      "platforms": [
        "windows-x64"
      ],
      "python_versions": [
        "3.11"
      ],
      "archive_url": "https://github.com/falken10vdl/bonsaiPR/releases/download/v0.8.5-alpha2604051935/bonsaiPR_py311-0.8.5-alpha2604051935-windows-x64.zip",
      "archive_size": 124488317,
      "archive_hash": "sha256:a5b59f441d6fc24c8339116fbf380275bd324a9552c4e374fa19fee88d4e8a5e"
    }
  ]
}