{
  "version": "v1",
  "blocklist": [],
  "data": [
    {
      "schema_version": "1.0.0",
      "id": "bonsaiPR",
      "name": "BonsaiPR",
      "tagline": "On-demand Bonsai builds with merged PRs for IfcOpenShell.",
      "version": "0.8.5-alpha260214",
      "type": "add-on",
      "maintainer": "falken10vdl <falken10vdl@gmail.com>",
      "license": [
        "SPDX:GPL-3.0-or-later"
      ],
      "blender_version_min": "4.2.0",
      "website": "https://github.com/falken10vdl/bonsaiPR",
      "permissions": {
        "network": "For update checks and remote asset downloads",
        "files": "Load and save IFCs, BCF, and other project files from disk",
        "clipboard": "Copy and paste error logs"
      },
      "tags": [
        "3D View",
        "Add Mesh",
        "Animation",
        "Camera",
        "Development",
        "Import-Export",
        "Lighting",
        "Material",
        "Modeling",
        "Mesh",
        "Node",
        "Object",
        "Pipeline",
        "Render",
        "Scene",
        "System",
        "User Interface",
        "UV"
      ],
      "platforms": [
        "linux-x64"
      ],
      "python_versions": [
        "3.11"
      ],
      "archive_url": "https://github.com/falken10vdl/bonsaiPR/releases/download/v0.8.5-alpha2602141135/bonsaiPR_py311-0.8.5-alpha2602141135-linux-x64.zip",
      "archive_size": 152527231,
      "archive_hash": "sha256:d97fc15f8ebf9e69ffe62f5ac0f10cc3e526cccc92d16bfb1b09c40910d3eefe"
    },
    {
      "schema_version": "1.0.0",
      "id": "bonsaiPR",
      "name": "BonsaiPR",
      "tagline": "On-demand Bonsai builds with merged PRs for IfcOpenShell.",
      "version": "0.8.5-alpha260214",
      "type": "add-on",
      "maintainer": "falken10vdl <falken10vdl@gmail.com>",
      "license": [
        "SPDX:GPL-3.0-or-later"
      ],
      "blender_version_min": "4.2.0",
      "website": "https://github.com/falken10vdl/bonsaiPR",
      "permissions": {
        "network": "For update checks and remote asset downloads",
        "files": "Load and save IFCs, BCF, and other project files from disk",
        "clipboard": "Copy and paste error logs"
      },
      "tags": [
        "3D View",
        "Add Mesh",
        "Animation",
        "Camera",
        "Development",
        "Import-Export",
        "Lighting",
        "Material",
        "Modeling",
        "Mesh",
        "Node",
        "Object",
        "Pipeline",
        "Render",
        "Scene",
        "System",
        "User Interface",
        "UV"
      ],
      "platforms": [
        "macos-x64"
      ],
      "python_versions": [
        "3.11"
      ],
      "archive_url": "https://github.com/falken10vdl/bonsaiPR/releases/download/v0.8.5-alpha2602141135/bonsaiPR_py311-0.8.5-alpha2602141135-macos-x64.zip",
      "archive_size": 139838844,
      "archive_hash": "sha256:e0b6b407b510b84aa359369a6a28a497fcbc82f3345649c0dedd0500c82f912e"
    },
    {
      "schema_version": "1.0.0",
      "id": "bonsaiPR",
      "name": "BonsaiPR",
      "tagline": "On-demand Bonsai builds with merged PRs for IfcOpenShell.",
      "version": "0.8.5-alpha260214",
      "type": "add-on",
      "maintainer": "falken10vdl <falken10vdl@gmail.com>",
      "license": [
        "SPDX:GPL-3.0-or-later"
      ],
      "blender_version_min": "4.2.0",
      "website": "https://github.com/falken10vdl/bonsaiPR",
      "permissions": {
        "network": "For update checks and remote asset downloads",
        "files": "Load and save IFCs, BCF, and other project files from disk",
        "clipboard": "Copy and paste error logs"
      },
      "tags": [
        "3D View",
        "Add Mesh",
        "Animation",
        "Camera",
        "Development",
        "Import-Export",
        "Lighting",
        "Material",
        "Modeling",
        "Mesh",
        "Node",
        "Object",
        "Pipeline",
        "Render",
        "Scene",
        "System",
        "User Interface",
        "UV"
      ],
      "platforms": [
        "macos-arm64"
      ],
      "python_versions": [
        "3.11"
      ],
      "archive_url": "https://github.com/falken10vdl/bonsaiPR/releases/download/v0.8.5-alpha2602141135/bonsaiPR_py311-0.8.5-alpha2602141135-macos-arm64.zip",
      "archive_size": 136853560,
      "archive_hash": "sha256:209604a402a334b7c034e4abdc2d23f9101c29e1b65d8a10d5ad1da85ec439f4"
    },
    {
      "schema_version": "1.0.0",
      "id": "bonsaiPR",
      "name": "BonsaiPR",
      "tagline": "On-demand Bonsai builds with merged PRs for IfcOpenShell.",
      "version": "0.8.5-alpha260214",
      "type": "add-on",
      "maintainer": "falken10vdl <falken10vdl@gmail.com>",
      "license": [
        "SPDX:GPL-3.0-or-later"
      ],
      "blender_version_min": "4.2.0",
      "website": "https://github.com/falken10vdl/bonsaiPR",
      "permissions": {
        "network": "For update checks and remote asset downloads",
        "files": "Load and save IFCs, BCF, and other project files from disk",
        "clipboard": "Copy and paste error logs"
      },
      "tags": [
        "3D View",
        "Add Mesh",
        "Animation",
        "Camera",
        "Development",
        "Import-Export",
        "Lighting",
        "Material",
        "Modeling",
        "Mesh",
        "Node",
        "Object",
        "Pipeline",
        "Render",
        "Scene",
        "System",
        "User Interface",
        "UV"
      ],
      "platforms": [
        "windows-x64"
      ],
      "python_versions": [
        "3.11"
      ],
      "archive_url": "https://github.com/falken10vdl/bonsaiPR/releases/download/v0.8.5-alpha2602141135/bonsaiPR_py311-0.8.5-alpha2602141135-windows-x64.zip",
      "archive_size": 121871598,
      "archive_hash": "sha256:10b287337f4ab5001543702b2ac60003e763eb495f8db485e5aeff868d53fd58"
    }
  ]
}